huaweicloudsdksis/__init__.py
huaweicloudsdksis/v1/__init__.py
huaweicloudsdksis/v1/sis_async_client.py
huaweicloudsdksis/v1/sis_client.py
huaweicloudsdksis/v1/model/__init__.py
huaweicloudsdksis/v1/model/analysis_info.py
huaweicloudsdksis/v1/model/analysis_info_result.py
huaweicloudsdksis/v1/model/collect_transcriber_job_request.py
huaweicloudsdksis/v1/model/collect_transcriber_job_response.py
huaweicloudsdksis/v1/model/config.py
huaweicloudsdksis/v1/model/create_vocabulary_request.py
huaweicloudsdksis/v1/model/create_vocabulary_response.py
huaweicloudsdksis/v1/model/custom_result.py
huaweicloudsdksis/v1/model/delete_vocabulary_request.py
huaweicloudsdksis/v1/model/delete_vocabulary_response.py
huaweicloudsdksis/v1/model/flash_result.py
huaweicloudsdksis/v1/model/flash_score_result.py
huaweicloudsdksis/v1/model/post_create_vocab_req.py
huaweicloudsdksis/v1/model/post_custom_tts_req.py
huaweicloudsdksis/v1/model/post_short_audio_req.py
huaweicloudsdksis/v1/model/post_transcriber_jobs.py
huaweicloudsdksis/v1/model/push_transcriber_jobs_request.py
huaweicloudsdksis/v1/model/push_transcriber_jobs_response.py
huaweicloudsdksis/v1/model/put_update_vocab_req.py
huaweicloudsdksis/v1/model/recognize_flash_asr_request.py
huaweicloudsdksis/v1/model/recognize_flash_asr_response.py
huaweicloudsdksis/v1/model/recognize_short_audio_request.py
huaweicloudsdksis/v1/model/recognize_short_audio_response.py
huaweicloudsdksis/v1/model/result.py
huaweicloudsdksis/v1/model/run_tts_request.py
huaweicloudsdksis/v1/model/run_tts_response.py
huaweicloudsdksis/v1/model/segment.py
huaweicloudsdksis/v1/model/sentences.py
huaweicloudsdksis/v1/model/show_vocabularies_params.py
huaweicloudsdksis/v1/model/show_vocabularies_request.py
huaweicloudsdksis/v1/model/show_vocabularies_response.py
huaweicloudsdksis/v1/model/show_vocabulary_request.py
huaweicloudsdksis/v1/model/show_vocabulary_response.py
huaweicloudsdksis/v1/model/transcriber_config.py
huaweicloudsdksis/v1/model/transcriber_result.py
huaweicloudsdksis-3.1.184.dist-info/METADATA
huaweicloudsdksis-3.1.184.dist-info/WHEEL
huaweicloudsdksis-3.1.184.dist-info/licenses/LICENSE
huaweicloudsdksis-3.1.184.dist-info/RECORD
